{
  "annotations": {
    "list": [
      {
        "builtIn": 1,
        "datasource": {
          "type": "grafana",
          "uid": "-- Grafana --"
        },
        "enable": true,
        "hide": true,
        "iconColor": "rgba(0, 211, 255, 1)",
        "name": "Annotations & Alerts",
        "type": "dashboard"
      }
    ]
  },
  "editable": true,
  "fiscalYearStartMonth": 0,
  "graphTooltip": 0,
  "id": null,
  "links": [],
  "liveNow": false,
  "panels": [
    {
      "datasource": {
        "type": "prometheus",
        "uid": "prometheus"
      },
      "fieldConfig": {
        "defaults": {
          "color": {
            "mode": "thresholds"
          },
          "mappings": [],
          "thresholds": {
            "mode": "absolute",
            "steps": [
              {
                "color": "green",
                "value": null
              },
              {
                "color": "red",
                "value": 10
              }
            ]
          },
          "unit": "reqps"
        },
        "overrides": []
      },
      "gridPos": {
        "h": 6,
        "w": 6,
        "x": 0,
        "y": 0
      },
      "id": 1,
      "options": {
        "colorMode": "value",
        "graphMode": "area",
        "justifyMode": "auto",
        "orientation": "auto",
        "reduceOptions": {
          "calcs": ["lastNotNull"],
          "fields": "",
          "values": false
        },
        "textMode": "auto"
      },
      "pluginVersion": "11.2.2",
      "targets": [
        {
          "editorMode": "code",
          "expr": "sum(rate(http_requests_total{service=\"core-api\"}[5m]))",
          "instant": true,
          "legendFormat": "",
          "range": false,
          "refId": "A"
        }
      ],
      "title": "Request Rate",
      "type": "stat"
    },
    {
      "datasource": {
        "type": "prometheus",
        "uid": "prometheus"
      },
      "fieldConfig": {
        "defaults": {
          "color": {
            "mode": "thresholds"
          },
          "mappings": [],
          "thresholds": {
            "mode": "absolute",
            "steps": [
              {
                "color": "green",
                "value": null
              },
              {
                "color": "red",
                "value": 1
              }
            ]
          },
          "unit": "reqps"
        },
        "overrides": []
      },
      "gridPos": {
        "h": 6,
        "w": 6,
        "x": 6,
        "y": 0
      },
      "id": 2,
      "options": {
        "colorMode": "value",
        "graphMode": "area",
        "justifyMode": "auto",
        "orientation": "auto",
        "reduceOptions": {
          "calcs": ["lastNotNull"],
          "fields": "",
          "values": false
        },
        "textMode": "auto"
      },
      "pluginVersion": "11.2.2",
      "targets": [
        {
          "editorMode": "code",
          "expr": "sum(rate(http_requests_total{service=\"core-api\",status_code=~\"5..\"}[5m]))",
          "instant": true,
          "legendFormat": "",
          "range": false,
          "refId": "A"
        }
      ],
      "title": "5xx Rate",
      "type": "stat"
    },
    {
      "datasource": {
        "type": "prometheus",
        "uid": "prometheus"
      },
      "fieldConfig": {
        "defaults": {
          "color": {
            "mode": "palette-classic"
          },
          "mappings": [],
          "unit": "s"
        },
        "overrides": []
      },
      "gridPos": {
        "h": 9,
        "w": 12,
        "x": 0,
        "y": 6
      },
      "id": 3,
      "options": {
        "legend": {
          "calcs": [],
          "displayMode": "list",
          "placement": "bottom",
          "showLegend": true
        },
        "tooltip": {
          "mode": "single",
          "sort": "none"
        }
      },
      "pluginVersion": "11.2.2",
      "targets": [
        {
          "editorMode": "code",
          "expr": "histogram_quantile(0.95, sum(rate(http_request_duration_seconds_bucket{service=\"core-api\"}[5m])) by (le))",
          "legendFormat": "p95",
          "range": true,
          "refId": "A"
        }
      ],
      "title": "Request Latency (p95)",
      "type": "timeseries"
    },
    {
      "datasource": {
        "type": "loki",
        "uid": "loki"
      },
      "gridPos": {
        "h": 9,
        "w": 12,
        "x": 12,
        "y": 6
      },
      "id": 4,
      "options": {
        "dedupStrategy": "none",
        "enableLogDetails": true,
        "prettifyLogMessage": false,
        "showCommonLabels": false,
        "showLabels": true,
        "showTime": true,
        "sortOrder": "Descending",
        "wrapLogMessage": false
      },
      "pluginVersion": "11.2.2",
      "targets": [
        {
          "editorMode": "code",
          "expr": "{service_name=\"unknown_service\"} |= \"core-api\"",
          "queryType": "range",
          "refId": "A"
        }
      ],
      "title": "Core API Logs",
      "type": "logs"
    }
  ],
  "refresh": "10s",
  "schemaVersion": 39,
  "style": "dark",
  "tags": ["core-api", "observability"],
  "templating": {
    "list": []
  },
  "time": {
    "from": "now-15m",
    "to": "now"
  },
  "timepicker": {},
  "timezone": "",
  "title": "Core API Observability",
  "uid": "core-api-observability",
  "version": 1,
  "weekStart": ""
}
